odoo/addons/pattern_import_export_synchronize/README.rst
odoo/addons/pattern_import_export_synchronize/__init__.py
odoo/addons/pattern_import_export_synchronize/__manifest__.py
odoo/addons/pattern_import_export_synchronize/demo/demo.xml
odoo/addons/pattern_import_export_synchronize/models/__init__.py
odoo/addons/pattern_import_export_synchronize/models/attachment_queue.py
odoo/addons/pattern_import_export_synchronize/models/attachment_synchronize_task.py
odoo/addons/pattern_import_export_synchronize/models/pattern_config.py
odoo/addons/pattern_import_export_synchronize/models/pattern_export_task.py
odoo/addons/pattern_import_export_synchronize/models/pattern_file.py
odoo/addons/pattern_import_export_synchronize/readme/CONTRIBUTORS.rst
odoo/addons/pattern_import_export_synchronize/readme/DESCRIPTION.rst
odoo/addons/pattern_import_export_synchronize/readme/USAGE.rst
odoo/addons/pattern_import_export_synchronize/security/ir.model.access.csv
odoo/addons/pattern_import_export_synchronize/static/description/index.html
odoo/addons/pattern_import_export_synchronize/tests/__init__.py
odoo/addons/pattern_import_export_synchronize/tests/test_export.py
odoo/addons/pattern_import_export_synchronize/tests/test_import.py
odoo/addons/pattern_import_export_synchronize/views/pattern_config_view.xml
odoo/addons/pattern_import_export_synchronize/views/pattern_export_task_view.xml
odoo/addons/pattern_import_export_synchronize/views/pattern_file_view.xml
odoo12_addon_pattern_import_export_synchronize-12.0.4.2.0.dist-info/METADATA
odoo12_addon_pattern_import_export_synchronize-12.0.4.2.0.dist-info/WHEEL
odoo12_addon_pattern_import_export_synchronize-12.0.4.2.0.dist-info/top_level.txt
odoo12_addon_pattern_import_export_synchronize-12.0.4.2.0.dist-info/RECORD
