Metadata-Version: 2.1
Name: odoo12-addon-pattern-import-export-synchronize
Version: 12.0.4.2.0
Summary: Attachment Synchronize using patterns
Home-page: https://github.com/OCA/pattern-import-export
Author: Akretion,Odoo Community Association (OCA)
Author-email: support@odoo-community.org
License: AGPL-3
Platform: UNKNOWN
Classifier: Programming Language :: Python
Classifier: Framework :: Odoo
Classifier: License :: OSI Approved :: GNU Affero General Public License v3
Requires-Python: >=3.5
Requires-Dist: mock
Requires-Dist: odoo12-addon-attachment-synchronize
Requires-Dist: odoo12-addon-pattern-import-export
Requires-Dist: odoo (<12.1dev,>=12.0a)
